llmring_server/__init__.py
llmring_server/cli.py
llmring_server/config.py
llmring_server/dependencies.py
llmring_server/main.py
llmring_server/py.typed
llmring_server/service.py
llmring_server/migrations/001_complete.sql
llmring_server/migrations/002_templates.sql
llmring_server/migrations/003_mcp.sql
llmring_server/migrations/004_remove_receipts.sql
llmring_server/migrations/005_templates_api_key.sql
llmring_server/migrations/006_project_scoping.sql
llmring_server/migrations/__init__.py
llmring_server/models/__init__.py
llmring_server/models/conversations.py
llmring_server/models/mcp.py
llmring_server/models/registry.py
llmring_server/models/templates.py
llmring_server/models/usage.py
llmring_server/routers/__init__.py
llmring_server/routers/conversations.py
llmring_server/routers/mcp.py
llmring_server/routers/registry.py
llmring_server/routers/templates.py
llmring_server/routers/usage.py
llmring_server/services/__init__.py
llmring_server/services/conversations.py
llmring_server/services/mcp_service.py
llmring_server/services/registry.py
llmring_server/services/templates.py
llmring_server/services/usage.py
llmring_server/utils/__init__.py
llmring_server/utils/auth_helpers.py
llmring_server-0.1.3.dist-info/METADATA
llmring_server-0.1.3.dist-info/WHEEL
llmring_server-0.1.3.dist-info/entry_points.txt
llmring_server-0.1.3.dist-info/licenses/LICENSE
llmring_server-0.1.3.dist-info/RECORD
