Metadata-Version: 2.4
Name: llmring-server
Version: 0.1.3
Summary: LLMRing core server: alias sync, receipts, and usage logging (key-scoped, no users)
Project-URL: Homepage, https://llmring.ai
Project-URL: Documentation, https://github.com/juanre/llmring/tree/main/llmring-server
Project-URL: Repository, https://github.com/juanre/llmring
Project-URL: Issues, https://github.com/juanre/llmring/issues
Author-email: Juan Reyero <juan@juanreyero.com>
License: MIT
License-File: LICENSE
Requires-Python: >=3.10
Requires-Dist: asyncpg>=0.29
Requires-Dist: click>=8.1.0
Requires-Dist: cryptography>=42.0.0
Requires-Dist: fastapi>=0.112
Requires-Dist: httpx>=0.27
Requires-Dist: pgdbm>=0.2.1
Requires-Dist: pydantic-settings>=2.4
Requires-Dist: pydantic>=2.11.7
Requires-Dist: redis>=5.0
Requires-Dist: uvicorn[standard]>=0.30
